Workbook

Sheet Inventario
A1: Producto | B1: Talla | C1: Cantidad disponible | D1: Notas | E1: Precio costo | F1: Precio venta | G1: Margen ($) | H1: Margen (%) | I1: Valor inventario (costo) | J1: Valor inventario (venta) | K1: Ganancia potencial
A2: Polo negro | B2: S | C2: 3 | E2: 25000 | F2: 60000 | G2: =IF(AND(E2<>"",F2<>""),F2-E2,"") -> 35000 | H2: =IF(AND(G2<>"",F2<>"",F2<>0),G2/F2,"") -> 0.58333333 | I2: =IF(AND(C2<>"",E2<>""),C2*E2,"") -> 75000 | J2: =IF(AND(C2<>"",F2<>""),C2*F2,"") -> 180000 | K2: =IF(AND(C2<>"",G2<>""),C2*G2,"") -> 105000
A3: Polo negro | B3: XL | C3: 3 | E3: 25000 | F3: 60000 | G3: =IF(AND(E3<>"",F3<>""),F3-E3,"") -> 35000 | H3: =IF(AND(G3<>"",F3<>"",F3<>0),G3/F3,"") -> 0.58333333 | I3: =IF(AND(C3<>"",E3<>""),C3*E3,"") -> 75000 | J3: =IF(AND(C3<>"",F3<>""),C3*F3,"") -> 180000 | K3: =IF(AND(C3<>"",G3<>""),C3*G3,"") -> 105000
A4: Polo negro | B4: m | D4: agotado, en un futuro | E4: 25000 | F4: 60000 | G4: =IF(AND(E4<>"",F4<>""),F4-E4,"") -> 35000 | H4: =IF(AND(G4<>"",F4<>"",F4<>0),G4/F4,"") -> 0.58333333 | I4: =IF(AND(C4<>"",E4<>""),C4*E4,"") | J4: =IF(AND(C4<>"",F4<>""),C4*F4,"") | K4: =IF(AND(C4<>"",G4<>""),C4*G4,"")
A5: Polo negro | B5: L | C5: 1 | E5: 25000 | F5: 60000 | G5: =IF(AND(E5<>"",F5<>""),F5-E5,"") -> 35000 | H5: =IF(AND(G5<>"",F5<>"",F5<>0),G5/F5,"") -> 0.58333333 | I5: =IF(AND(C5<>"",E5<>""),C5*E5,"") -> 25000 | J5: =IF(AND(C5<>"",F5<>""),C5*F5,"") -> 60000 | K5: =IF(AND(C5<>"",G5<>""),C5*G5,"") -> 35000
A6: Polo Blanco | B6: XL | C6: 5 | E6: 25000 | F6: 60000 | G6: =IF(AND(E6<>"",F6<>""),F6-E6,"") -> 35000 | H6: =IF(AND(G6<>"",F6<>"",F6<>0),G6/F6,"") -> 0.58333333 | I6: =IF(AND(C6<>"",E6<>""),C6*E6,"") -> 125000 | J6: =IF(AND(C6<>"",F6<>""),C6*F6,"") -> 300000 | K6: =IF(AND(C6<>"",G6<>""),C6*G6,"") -> 175000
A7: Polo Blanco | B7: L | C7: 0 | D7: agotado, en un futuro | E7: 25000 | F7: 60000 | G7: =IF(AND(E7<>"",F7<>""),F7-E7,"") -> 35000 | H7: =IF(AND(G7<>"",F7<>"",F7<>0),G7/F7,"") -> 0.58333333 | I7: =IF(AND(C7<>"",E7<>""),C7*E7,"") -> 0 | J7: =IF(AND(C7<>"",F7<>""),C7*F7,"") -> 0 | K7: =IF(AND(C7<>"",G7<>""),C7*G7,"") -> 0
A8: Polo Blanco | B8: S | C8: 2 | E8: 25000 | F8: 60000 | G8: =IF(AND(E8<>"",F8<>""),F8-E8,"") -> 35000 | H8: =IF(AND(G8<>"",F8<>"",F8<>0),G8/F8,"") -> 0.58333333 | I8: =IF(AND(C8<>"",E8<>""),C8*E8,"") -> 50000 | J8: =IF(AND(C8<>"",F8<>""),C8*F8,"") -> 120000 | K8: =IF(AND(C8<>"",G8<>""),C8*G8,"") -> 70000
A9: Polo Blanco | B9: M | C9: 5 | E9: 25000 | F9: 60000 | G9: =IF(AND(E9<>"",F9<>""),F9-E9,"") -> 35000 | H9: =IF(AND(G9<>"",F9<>"",F9<>0),G9/F9,"") -> 0.58333333 | I9: =IF(AND(C9<>"",E9<>""),C9*E9,"") -> 125000 | J9: =IF(AND(C9<>"",F9<>""),C9*F9,"") -> 300000 | K9: =IF(AND(C9<>"",G9<>""),C9*G9,"") -> 175000
A10: Set Rojo | B10: M | C10: 1 | E10: 25000 | F10: 100000 | G10: =IF(AND(E10<>"",F10<>""),F10-E10,"") -> 75000 | H10: =IF(AND(G10<>"",F10<>"",F10<>0),G10/F10,"") -> 0.75 | I10: =IF(AND(C10<>"",E10<>""),C10*E10,"") -> 25000 | J10: =IF(AND(C10<>"",F10<>""),C10*F10,"") -> 100000 | K10: =IF(AND(C10<>"",G10<>""),C10*G10,"") -> 75000
A11: Set Rojo | B11: L | C11: 1 | E11: 25000 | F11: 100000 | G11: =IF(AND(E11<>"",F11<>""),F11-E11,"") -> 75000 | H11: =IF(AND(G11<>"",F11<>"",F11<>0),G11/F11,"") -> 0.75 | I11: =IF(AND(C11<>"",E11<>""),C11*E11,"") -> 25000 | J11: =IF(AND(C11<>"",F11<>""),C11*F11,"") -> 100000 | K11: =IF(AND(C11<>"",G11<>""),C11*G11,"") -> 75000
A12: Set Rojo | B12: XL | C12: 1 | E12: 25000 | F12: 100000 | G12: =IF(AND(E12<>"",F12<>""),F12-E12,"") -> 75000 | H12: =IF(AND(G12<>"",F12<>"",F12<>0),G12/F12,"") -> 0.75 | I12: =IF(AND(C12<>"",E12<>""),C12*E12,"") -> 25000 | J12: =IF(AND(C12<>"",F12<>""),C12*F12,"") -> 100000 | K12: =IF(AND(C12<>"",G12<>""),C12*G12,"") -> 75000
A13: Camisa + Pantalón | B13: M | C13: 0 | D13: VENDIDO | E13: 47900 | F13: 100000 | G13: =IF(AND(E13<>"",F13<>""),F13-E13,"") -> 52100 | H13: =IF(AND(G13<>"",F13<>"",F13<>0),G13/F13,"") -> 0.521 | I13: =IF(AND(C13<>"",E13<>""),C13*E13,"") -> 0 | J13: =IF(AND(C13<>"",F13<>""),C13*F13,"") -> 0 | K13: =IF(AND(C13<>"",G13<>""),C13*G13,"") -> 0
A14: Camisa + Pantalón | B14: L | C14: 2 | E14: 47900 | F14: 100000 | G14: =IF(AND(E14<>"",F14<>""),F14-E14,"") -> 52100 | H14: =IF(AND(G14<>"",F14<>"",F14<>0),G14/F14,"") -> 0.521 | I14: =IF(AND(C14<>"",E14<>""),C14*E14,"") -> 95800 | J14: =IF(AND(C14<>"",F14<>""),C14*F14,"") -> 200000 | K14: =IF(AND(C14<>"",G14<>""),C14*G14,"") -> 104200
A15: Set Beige | B15: XL | C15: 2 | E15: 25000 | F15: 100000 | G15: =IF(AND(E15<>"",F15<>""),F15-E15,"") -> 75000 | H15: =IF(AND(G15<>"",F15<>"",F15<>0),G15/F15,"") -> 0.75 | I15: =IF(AND(C15<>"",E15<>""),C15*E15,"") -> 50000 | J15: =IF(AND(C15<>"",F15<>""),C15*F15,"") -> 200000 | K15: =IF(AND(C15<>"",G15<>""),C15*G15,"") -> 150000
A16: Set Beige | B16: M | C16: 0 | D16: agotado, en un futuro | E16: 25000 | F16: 100000 | G16: =IF(AND(E16<>"",F16<>""),F16-E16,"") -> 75000 | H16: =IF(AND(G16<>"",F16<>"",F16<>0),G16/F16,"") -> 0.75 | I16: =IF(AND(C16<>"",E16<>""),C16*E16,"") -> 0 | J16: =IF(AND(C16<>"",F16<>""),C16*F16,"") -> 0 | K16: =IF(AND(C16<>"",G16<>""),C16*G16,"") -> 0
A17: Set Beige | B17: S | C17: 0 | E17: 25000 | F17: 100000 | G17: =IF(AND(E17<>"",F17<>""),F17-E17,"") -> 75000 | H17: =IF(AND(G17<>"",F17<>"",F17<>0),G17/F17,"") -> 0.75 | I17: =IF(AND(C17<>"",E17<>""),C17*E17,"") -> 0 | J17: =IF(AND(C17<>"",F17<>""),C17*F17,"") -> 0 | K17: =IF(AND(C17<>"",G17<>""),C17*G17,"") -> 0
A18: Set Beige | B18: L | C18: 2 | E18: 25000 | F18: 100000 | G18: =IF(AND(E18<>"",F18<>""),F18-E18,"") -> 75000 | H18: =IF(AND(G18<>"",F18<>"",F18<>0),G18/F18,"") -> 0.75 | I18: =IF(AND(C18<>"",E18<>""),C18*E18,"") -> 50000 | J18: =IF(AND(C18<>"",F18<>""),C18*F18,"") -> 200000 | K18: =IF(AND(C18<>"",G18<>""),C18*G18,"") -> 150000
A19: Set corto negro | B19: M | C19: 1 | E19: 30000 | F19: 85000 | G19: =IF(AND(E19<>"",F19<>""),F19-E19,"") -> 55000 | H19: =IF(AND(G19<>"",F19<>"",F19<>0),G19/F19,"") -> 0.64705882 | I19: =IF(AND(C19<>"",E19<>""),C19*E19,"") -> 30000 | J19: =IF(AND(C19<>"",F19<>""),C19*F19,"") -> 85000 | K19: =IF(AND(C19<>"",G19<>""),C19*G19,"") -> 55000
A20: Set corto negro | B20: S | C20: 0 | D20: agotado, en un futuro | E20: 30000 | F20: 85000 | G20: =IF(AND(E20<>"",F20<>""),F20-E20,"") -> 55000 | H20: =IF(AND(G20<>"",F20<>"",F20<>0),G20/F20,"") -> 0.64705882 | I20: =IF(AND(C20<>"",E20<>""),C20*E20,"") -> 0 | J20: =IF(AND(C20<>"",F20<>""),C20*F20,"") -> 0 | K20: =IF(AND(C20<>"",G20<>""),C20*G20,"") -> 0
A21: Set corto negro | B21: XL | C21: 0 | D21: agotado, en un futuro | E21: 30000 | F21: 85000 | G21: =IF(AND(E21<>"",F21<>""),F21-E21,"") -> 55000 | H21: =IF(AND(G21<>"",F21<>"",F21<>0),G21/F21,"") -> 0.64705882 | I21: =IF(AND(C21<>"",E21<>""),C21*E21,"") -> 0 | J21: =IF(AND(C21<>"",F21<>""),C21*F21,"") -> 0 | K21: =IF(AND(C21<>"",G21<>""),C21*G21,"") -> 0
A22: Set corto negro | B22: L | C22: 1 | E22: 30000 | F22: 85000 | G22: =IF(AND(E22<>"",F22<>""),F22-E22,"") -> 55000 | H22: =IF(AND(G22<>"",F22<>"",F22<>0),G22/F22,"") -> 0.64705882 | I22: =IF(AND(C22<>"",E22<>""),C22*E22,"") -> 30000 | J22: =IF(AND(C22<>"",F22<>""),C22*F22,"") -> 85000 | K22: =IF(AND(C22<>"",G22<>""),C22*G22,"") -> 55000
A23: Set Negro | B23: L | C23: 2 | E23: 25000 | F23: 100000 | G23: =IF(AND(E23<>"",F23<>""),F23-E23,"") -> 75000 | H23: =IF(AND(G23<>"",F23<>"",F23<>0),G23/F23,"") -> 0.75 | I23: =IF(AND(C23<>"",E23<>""),C23*E23,"") -> 50000 | J23: =IF(AND(C23<>"",F23<>""),C23*F23,"") -> 200000 | K23: =IF(AND(C23<>"",G23<>""),C23*G23,"") -> 150000
A24: Set Negro | D24: agotado, en un futuro | E24: 25000 | F24: 100000 | G24: =IF(AND(E24<>"",F24<>""),F24-E24,"") -> 75000 | H24: =IF(AND(G24<>"",F24<>"",F24<>0),G24/F24,"") -> 0.75 | I24: =IF(AND(C24<>"",E24<>""),C24*E24,"") | J24: =IF(AND(C24<>"",F24<>""),C24*F24,"") | K24: =IF(AND(C24<>"",G24<>""),C24*G24,"")
A25: Set Negro | D25: agotado, en un futuro | E25: 25000 | F25: 100000 | G25: =IF(AND(E25<>"",F25<>""),F25-E25,"") -> 75000 | H25: =IF(AND(G25<>"",F25<>"",F25<>0),G25/F25,"") -> 0.75 | I25: =IF(AND(C25<>"",E25<>""),C25*E25,"") | J25: =IF(AND(C25<>"",F25<>""),C25*F25,"") | K25: =IF(AND(C25<>"",G25<>""),C25*G25,"")
A26: Set Negro | B26: M | C26: 1 | E26: 25000 | F26: 100000 | G26: =IF(AND(E26<>"",F26<>""),F26-E26,"") -> 75000 | H26: =IF(AND(G26<>"",F26<>"",F26<>0),G26/F26,"") -> 0.75 | I26: =IF(AND(C26<>"",E26<>""),C26*E26,"") -> 25000 | J26: =IF(AND(C26<>"",F26<>""),C26*F26,"") -> 100000 | K26: =IF(AND(C26<>"",G26<>""),C26*G26,"") -> 75000
A27: Set corto Beige | B27: M | C27: 0 | E27: 30000 | F27: 85000 | G27: =IF(AND(E27<>"",F27<>""),F27-E27,"") -> 55000 | H27: =IF(AND(G27<>"",F27<>"",F27<>0),G27/F27,"") -> 0.64705882 | I27: =IF(AND(C27<>"",E27<>""),C27*E27,"") -> 0 | J27: =IF(AND(C27<>"",F27<>""),C27*F27,"") -> 0 | K27: =IF(AND(C27<>"",G27<>""),C27*G27,"") -> 0
A28: Set corto Beige | B28: XL | C28: 0 | E28: 30000 | F28: 85000 | G28: =IF(AND(E28<>"",F28<>""),F28-E28,"") -> 55000 | H28: =IF(AND(G28<>"",F28<>"",F28<>0),G28/F28,"") -> 0.64705882 | I28: =IF(AND(C28<>"",E28<>""),C28*E28,"") -> 0 | J28: =IF(AND(C28<>"",F28<>""),C28*F28,"") -> 0 | K28: =IF(AND(C28<>"",G28<>""),C28*G28,"") -> 0
A29: Set corto Beige | B29: S | C29: 0 | E29: 30000 | F29: 85000 | G29: =IF(AND(E29<>"",F29<>""),F29-E29,"") -> 55000 | H29: =IF(AND(G29<>"",F29<>"",F29<>0),G29/F29,"") -> 0.64705882 | I29: =IF(AND(C29<>"",E29<>""),C29*E29,"") -> 0 | J29: =IF(AND(C29<>"",F29<>""),C29*F29,"") -> 0 | K29: =IF(AND(C29<>"",G29<>""),C29*G29,"") -> 0
A30: Set corto Beige | B30: L | C30: 2 | E30: 30000 | F30: 85000 | G30: =IF(AND(E30<>"",F30<>""),F30-E30,"") -> 55000 | H30: =IF(AND(G30<>"",F30<>"",F30<>0),G30/F30,"") -> 0.64705882 | I30: =IF(AND(C30<>"",E30<>""),C30*E30,"") -> 60000 | J30: =IF(AND(C30<>"",F30<>""),C30*F30,"") -> 170000 | K30: =IF(AND(C30<>"",G30<>""),C30*G30,"") -> 110000
A31: Set Blanco | B31: S | C31: 2 | E31: 25000 | F31: 100000 | G31: =IF(AND(E31<>"",F31<>""),F31-E31,"") -> 75000 | H31: =IF(AND(G31<>"",F31<>"",F31<>0),G31/F31,"") -> 0.75 | I31: =IF(AND(C31<>"",E31<>""),C31*E31,"") -> 50000 | J31: =IF(AND(C31<>"",F31<>""),C31*F31,"") -> 200000 | K31: =IF(AND(C31<>"",G31<>""),C31*G31,"") -> 150000
A32: Set Blanco | B32: M | C32: 3 | E32: 25000 | F32: 100000 | G32: =IF(AND(E32<>"",F32<>""),F32-E32,"") -> 75000 | H32: =IF(AND(G32<>"",F32<>"",F32<>0),G32/F32,"") -> 0.75 | I32: =IF(AND(C32<>"",E32<>""),C32*E32,"") -> 75000 | J32: =IF(AND(C32<>"",F32<>""),C32*F32,"") -> 300000 | K32: =IF(AND(C32<>"",G32<>""),C32*G32,"") -> 225000
A33: Set Blanco | B33: L | C33: 2 | E33: 25000 | F33: 100000 | G33: =IF(AND(E33<>"",F33<>""),F33-E33,"") -> 75000 | H33: =IF(AND(G33<>"",F33<>"",F33<>0),G33/F33,"") -> 0.75 | I33: =IF(AND(C33<>"",E33<>""),C33*E33,"") -> 50000 | J33: =IF(AND(C33<>"",F33<>""),C33*F33,"") -> 200000 | K33: =IF(AND(C33<>"",G33<>""),C33*G33,"") -> 150000
A34: Set Blanco | B34: XL | C34: 3 | E34: 25000 | F34: 100000 | G34: =IF(AND(E34<>"",F34<>""),F34-E34,"") -> 75000 | H34: =IF(AND(G34<>"",F34<>"",F34<>0),G34/F34,"") -> 0.75 | I34: =IF(AND(C34<>"",E34<>""),C34*E34,"") -> 75000 | J34: =IF(AND(C34<>"",F34<>""),C34*F34,"") -> 300000 | K34: =IF(AND(C34<>"",G34<>""),C34*G34,"") -> 225000
A35: Urbano Fit | B35: S | C35: 1 | E35: 35000 | F35: 85000 | G35: =IF(AND(E35<>"",F35<>""),F35-E35,"") -> 50000 | H35: =IF(AND(G35<>"",F35<>"",F35<>0),G35/F35,"") -> 0.58823529 | I35: =IF(AND(C35<>"",E35<>""),C35*E35,"") -> 35000 | J35: =IF(AND(C35<>"",F35<>""),C35*F35,"") -> 85000 | K35: =IF(AND(C35<>"",G35<>""),C35*G35,"") -> 50000
A36: Set corto Blanco + Beige | B36: S | C36: 0 | E36: 28373 | F36: 85000 | G36: =IF(AND(E36<>"",F36<>""),F36-E36,"") -> 56627 | H36: =IF(AND(G36<>"",F36<>"",F36<>0),G36/F36,"") -> 0.6662 | I36: =IF(AND(C36<>"",E36<>""),C36*E36,"") -> 0 | J36: =IF(AND(C36<>"",F36<>""),C36*F36,"") -> 0 | K36: =IF(AND(C36<>"",G36<>""),C36*G36,"") -> 0
A37: Set corto Blanco + Beige | B37: XL | C37: 2 | E37: 28373 | F37: 85000 | G37: =IF(AND(E37<>"",F37<>""),F37-E37,"") -> 56627 | H37: =IF(AND(G37<>"",F37<>"",F37<>0),G37/F37,"") -> 0.6662 | I37: =IF(AND(C37<>"",E37<>""),C37*E37,"") -> 56746 | J37: =IF(AND(C37<>"",F37<>""),C37*F37,"") -> 170000 | K37: =IF(AND(C37<>"",G37<>""),C37*G37,"") -> 113254
... A41: Polo albaricoque | B41: L | C41: 1 | E41: 16000 | F41: 55000 | G41: =IF(AND(E41<>"",F41<>""),F41-E41,"") -> 39000 | H41: =IF(AND(G41<>"",F41<>"",F41<>0),G41/F41,"") -> 0.70909091 | I41: =IF(AND(C41<>"",E41<>""),C41*E41,"") -> 16000 | J41: =IF(AND(C41<>"",F41<>""),C41*F41,"") -> 55000 | K41: =IF(AND(C41<>"",G41<>""),C41*G41,"") -> 39000
A42: Pantalón caqui | B42: 28 | C42: 0 | D42: VENDIDO | E42: 31000 | F42: 60000 | G42: =IF(AND(E42<>"",F42<>""),F42-E42,"") -> 29000 | H42: =IF(AND(G42<>"",F42<>"",F42<>0),G42/F42,"") -> 0.48333333 | I42: =IF(AND(C42<>"",E42<>""),C42*E42,"") -> 0 | J42: =IF(AND(C42<>"",F42<>""),C42*F42,"") -> 0 | K42: =IF(AND(C42<>"",G42<>""),C42*G42,"") -> 0
A43: Pantalón caqui | B43: 30 | C43: 0 | D43: VENDIDO | E43: 31000 | F43: 60000 | G43: =IF(AND(E43<>"",F43<>""),F43-E43,"") -> 29000 | H43: =IF(AND(G43<>"",F43<>"",F43<>0),G43/F43,"") -> 0.48333333 | I43: =IF(AND(C43<>"",E43<>""),C43*E43,"") -> 0 | J43: =IF(AND(C43<>"",F43<>""),C43*F43,"") -> 0 | K43: =IF(AND(C43<>"",G43<>""),C43*G43,"") -> 0
A44: Pantalón caqui | B44: 31 | C44: 0 | D44: VENDIDO | E44: 31000 | F44: 60000 | G44: =IF(AND(E44<>"",F44<>""),F44-E44,"") -> 29000 | H44: =IF(AND(G44<>"",F44<>"",F44<>0),G44/F44,"") -> 0.48333333 | I44: =IF(AND(C44<>"",E44<>""),C44*E44,"") -> 0 | J44: =IF(AND(C44<>"",F44<>""),C44*F44,"") -> 0 | K44: =IF(AND(C44<>"",G44<>""),C44*G44,"") -> 0
A45: Pantalón caqui | B45: 32 | C45: 0 | D45: VENDIDO | E45: 31000 | F45: 60000 | G45: =IF(AND(E45<>"",F45<>""),F45-E45,"") -> 29000 | H45: =IF(AND(G45<>"",F45<>"",F45<>0),G45/F45,"") -> 0.48333333 | I45: =IF(AND(C45<>"",E45<>""),C45*E45,"") -> 0 | J45: =IF(AND(C45<>"",F45<>""),C45*F45,"") -> 0 | K45: =IF(AND(C45<>"",G45<>""),C45*G45,"") -> 0
A46: Pantalón caqui | B46: 34 | C46: 0 | D46: VENDIDO | E46: 31000 | F46: 60000 | G46: =IF(AND(E46<>"",F46<>""),F46-E46,"") -> 29000 | H46: =IF(AND(G46<>"",F46<>"",F46<>0),G46/F46,"") -> 0.48333333 | I46: =IF(AND(C46<>"",E46<>""),C46*E46,"") -> 0 | J46: =IF(AND(C46<>"",F46<>""),C46*F46,"") -> 0 | K46: =IF(AND(C46<>"",G46<>""),C46*G46,"") -> 0
A47: Camisetas negro | B47: XL | C47: 2 | E47: 25000 | F47: 60000 | G47: =IF(AND(E47<>"",F47<>""),F47-E47,"") -> 35000 | H47: =IF(AND(G47<>"",F47<>"",F47<>0),G47/F47,"") -> 0.58333333 | I47: =IF(AND(C47<>"",E47<>""),C47*E47,"") -> 50000 | J47: =IF(AND(C47<>"",F47<>""),C47*F47,"") -> 120000 | K47: =IF(AND(C47<>"",G47<>""),C47*G47,"") -> 70000
A48: Camisetas negro | B48: S | C48: 2 | E48: 25000 | F48: 60000 | G48: =IF(AND(E48<>"",F48<>""),F48-E48,"") -> 35000 | H48: =IF(AND(G48<>"",F48<>"",F48<>0),G48/F48,"") -> 0.58333333 | I48: =IF(AND(C48<>"",E48<>""),C48*E48,"") -> 50000 | J48: =IF(AND(C48<>"",F48<>""),C48*F48,"") -> 120000 | K48: =IF(AND(C48<>"",G48<>""),C48*G48,"") -> 70000
A49: Camisetas negro | B49: L | C49: 3 | D49: NO, HA LLEGADO | E49: 25000 | F49: 60000 | G49: =IF(AND(E49<>"",F49<>""),F49-E49,"") -> 35000 | H49: =IF(AND(G49<>"",F49<>"",F49<>0),G49/F49,"") -> 0.58333333 | I49: =IF(AND(C49<>"",E49<>""),C49*E49,"") -> 75000 | J49: =IF(AND(C49<>"",F49<>""),C49*F49,"") -> 180000 | K49: =IF(AND(C49<>"",G49<>""),C49*G49,"") -> 105000
A50: Camisetas negro | B50: M | C50: 2 | E50: 25000 | F50: 60000 | G50: =IF(AND(E50<>"",F50<>""),F50-E50,"") -> 35000 | H50: =IF(AND(G50<>"",F50<>"",F50<>0),G50/F50,"") -> 0.58333333 | I50: =IF(AND(C50<>"",E50<>""),C50*E50,"") -> 50000 | J50: =IF(AND(C50<>"",F50<>""),C50*F50,"") -> 120000 | K50: =IF(AND(C50<>"",G50<>""),C50*G50,"") -> 70000
A51: Camiseta Gris | B51: M | C51: 2 | E51: 20000 | F51: 60000 | G51: =IF(AND(E51<>"",F51<>""),F51-E51,"") -> 40000 | H51: =IF(AND(G51<>"",F51<>"",F51<>0),G51/F51,"") -> 0.66666667 | I51: =IF(AND(C51<>"",E51<>""),C51*E51,"") -> 40000 | J51: =IF(AND(C51<>"",F51<>""),C51*F51,"") -> 120000 | K51: =IF(AND(C51<>"",G51<>""),C51*G51,"") -> 80000
A52: Camisetas Azul oscuro | B52: M | C52: 2 | E52: 25000 | F52: 60000 | G52: =IF(AND(E52<>"",F52<>""),F52-E52,"") -> 35000 | H52: =IF(AND(G52<>"",F52<>"",F52<>0),G52/F52,"") -> 0.58333333 | I52: =IF(AND(C52<>"",E52<>""),C52*E52,"") -> 50000 | J52: =IF(AND(C52<>"",F52<>""),C52*F52,"") -> 120000 | K52: =IF(AND(C52<>"",G52<>""),C52*G52,"") -> 70000
A53: Camisetas Azul oscuro | B53: L | C53: 2 | E53: 25000 | F53: 60000 | G53: =IF(AND(E53<>"",F53<>""),F53-E53,"") -> 35000 | H53: =IF(AND(G53<>"",F53<>"",F53<>0),G53/F53,"") -> 0.58333333 | I53: =IF(AND(C53<>"",E53<>""),C53*E53,"") -> 50000 | J53: =IF(AND(C53<>"",F53<>""),C53*F53,"") -> 120000 | K53: =IF(AND(C53<>"",G53<>""),C53*G53,"") -> 70000
A54: Camisetas Azul oscuro | B54: XL | C54: 1 | D54: NO, HA LLEGADO | E54: 25000 | F54: 60000 | G54: =IF(AND(E54<>"",F54<>""),F54-E54,"") -> 35000 | H54: =IF(AND(G54<>"",F54<>"",F54<>0),G54/F54,"") -> 0.58333333 | I54: =IF(AND(C54<>"",E54<>""),C54*E54,"") -> 25000 | J54: =IF(AND(C54<>"",F54<>""),C54*F54,"") -> 60000 | K54: =IF(AND(C54<>"",G54<>""),C54*G54,"") -> 35000
A55: Camisetas Azul oscuro | B55: S | C55: 0 | D55: NO, HA LLEGADO | E55: 25000 | G55: =IF(AND(E55<>"",F56<>""),F56-E55,"") -> 35000 | H55: =IF(AND(G55<>"",F56<>"",F56<>0),G55/F56,"") -> 0.58333333 | I55: =IF(AND(C55<>"",E55<>""),C55*E55,"") -> 0 | J55: =IF(AND(C55<>"",F56<>""),C55*F56,"") -> 0 | K55: =IF(AND(C55<>"",G55<>""),C55*G55,"") -> 0
A56: Pantalón negro | B56: 28 | C56: 0 | D56: NO, HA LLEGADO | E56: 26000 | F56: 60000 | G56: =IF(AND(E56<>"",F57<>""),F57-E56,"") -> 34000 | H56: =IF(AND(G56<>"",F57<>"",F57<>0),G56/F57,"") -> 0.56666667 | I56: =IF(AND(C56<>"",E56<>""),C56*E56,"") -> 0 | J56: =IF(AND(C56<>"",F57<>""),C56*F57,"") -> 0 | K56: =IF(AND(C56<>"",G56<>""),C56*G56,"") -> 0
A57: Pantalón negro | B57: 30 | C57: 1 | E57: 26000 | F57: 60000 | G57: =IF(AND(E57<>"",F58<>""),F58-E57,"") -> 34000 | H57: =IF(AND(G57<>"",F58<>"",F58<>0),G57/F58,"") -> 0.56666667 | I57: =IF(AND(C57<>"",E57<>""),C57*E57,"") -> 26000 | J57: =IF(AND(C57<>"",F58<>""),C57*F58,"") -> 60000 | K57: =IF(AND(C57<>"",G57<>""),C57*G57,"") -> 34000
A58: Pantalón negro | B58: 31 | C58: 1 | E58: 26000 | F58: 60000 | G58: =IF(AND(E58<>"",F59<>""),F59-E58,"") -> 34000 | H58: =IF(AND(G58<>"",F59<>"",F59<>0),G58/F59,"") -> 0.56666667 | I58: =IF(AND(C58<>"",E58<>""),C58*E58,"") -> 26000 | J58: =IF(AND(C58<>"",F59<>""),C58*F59,"") -> 60000 | K58: =IF(AND(C58<>"",G58<>""),C58*G58,"") -> 34000
A59: Pantalón negro | B59: 32 | C59: 0 | D59: NO, HA LLEGADO | E59: 26000 | F59: 60000 | G59: =IF(AND(E59<>"",F60<>""),F60-E59,"") -> 34000 | H59: =IF(AND(G59<>"",F60<>"",F60<>0),G59/F60,"") -> 0.56666667 | I59: =IF(AND(C59<>"",E59<>""),C59*E59,"") -> 0 | J59: =IF(AND(C59<>"",F60<>""),C59*F60,"") -> 0 | K59: =IF(AND(C59<>"",G59<>""),C59*G59,"") -> 0
A60: Pantalón negro | B60: 34 | C60: 0 | D60: NO, HA LLEGADO | E60: 26000 | F60: 60000 | G60: =IF(AND(E60<>"",F61<>""),F61-E60,"") -> 34000 | H60: =IF(AND(G60<>"",F61<>"",F61<>0),G60/F61,"") -> 0.56666667 | I60: =IF(AND(C60<>"",E60<>""),C60*E60,"") -> 0 | J60: =IF(AND(C60<>"",F61<>""),C60*F61,"") -> 0 | K60: =IF(AND(C60<>"",G60<>""),C60*G60,"") -> 0
A61: Camiseta Vinotinto | B61: S | C61: 0 | D61: NO, HA LLEGADO | E61: 25000 | F61: 60000 | G61: =IF(AND(E61<>"",F62<>""),F62-E61,"") -> 35000 | H61: =IF(AND(G61<>"",F62<>"",F62<>0),G61/F62,"") -> 0.58333333 | I61: =IF(AND(C61<>"",E61<>""),C61*E61,"") -> 0 | J61: =IF(AND(C61<>"",F62<>""),C61*F62,"") -> 0 | K61: =IF(AND(C61<>"",G61<>""),C61*G61,"") -> 0
A62: Camiseta Vinotinto | B62: M | C62: 1 | E62: 25000 | F62: 60000 | G62: =IF(AND(E62<>"",F62<>""),F62-E62,"") -> 35000 | H62: =IF(AND(G62<>"",F62<>"",F62<>0),G62/F62,"") -> 0.58333333 | I62: =IF(AND(C62<>"",E62<>""),C62*E62,"") -> 25000 | J62: =IF(AND(C62<>"",F62<>""),C62*F62,"") -> 60000 | K62: =IF(AND(C62<>"",G62<>""),C62*G62,"") -> 35000
A63: Camiseta Vinotinto | B63: L | C63: 2 | E63: 25000 | F63: 60000 | G63: =IF(AND(E63<>"",F63<>""),F63-E63,"") -> 35000 | H63: =IF(AND(G63<>"",F63<>"",F63<>0),G63/F63,"") -> 0.58333333 | I63: =IF(AND(C63<>"",E63<>""),C63*E63,"") -> 50000 | J63: =IF(AND(C63<>"",F63<>""),C63*F63,"") -> 120000 | K63: =IF(AND(C63<>"",G63<>""),C63*G63,"") -> 70000
A64: Camiseta Vinotinto | B64: XL | C64: 1 | E64: 25000 | F64: 60000 | G64: =IF(AND(E64<>"",F64<>""),F64-E64,"") -> 35000 | H64: =IF(AND(G64<>"",F64<>"",F64<>0),G64/F64,"") -> 0.58333333 | I64: =IF(AND(C64<>"",E64<>""),C64*E64,"") -> 25000 | J64: =IF(AND(C64<>"",F64<>""),C64*F64,"") -> 60000 | K64: =IF(AND(C64<>"",G64<>""),C64*G64,"") -> 35000
A65: TOTAL GENERAL | C65: =SUM(C2:C64) -> 80 | K65: =SUM(K2:K64) -> 3979097
A67: Cómo usar las columnas nuevas: | I67: =SUM(I2:I64) -> 2095903 | J67: =SUM(J2:J64) -> 6075000
A68: Escribe el "Precio costo" (lo que te costó la prenda) y el "Precio venta" (a como la vendes) en cada fila, en azul. El margen y las ganancias se calculan solos.

Sheet Resumen por producto
A1: Producto | B1: Total disponible | C1: Ganancia potencial
A2: Polo negro | B2: =SUMIFS(Inventario!C2:C64,Inventario!A2:A64,A2) -> 7 | C2: =SUMIFS(Inventario!$K$2:$K$64,Inventario!$A$2:$A$64,A2) -> 245000
A3: Polo Blanco | B3: =SUMIFS(Inventario!C2:C64,Inventario!A2:A64,A3) -> 12 | C3: =SUMIFS(Inventario!$K$2:$K$64,Inventario!$A$2:$A$64,A3) -> 420000
A4: Set Rojo | B4: =SUMIFS(Inventario!C2:C64,Inventario!A2:A64,A4) -> 3 | C4: =SUMIFS(Inventario!$K$2:$K$64,Inventario!$A$2:$A$64,A4) -> 225000
A5: Camisa + Pantalón | B5: =SUMIFS(Inventario!C2:C64,Inventario!A2:A64,A5) -> 2 | C5: =SUMIFS(Inventario!$K$2:$K$64,Inventario!$A$2:$A$64,A5) -> 104200
A6: Camiseta Gris | B6: =SUMIFS(Inventario!C3:C65,Inventario!A3:A65,A6) -> 2 | C6: =SUMIFS(Inventario!$K$2:$K$64,Inventario!$A$2:$A$64,A6) -> 80000
A7: Set Beige | B7: =SUMIFS(Inventario!C2:C64,Inventario!A2:A64,A7) -> 4 | C7: =SUMIFS(Inventario!$K$2:$K$64,Inventario!$A$2:$A$64,A7) -> 300000
A8: Set corto negro | B8: =SUMIFS(Inventario!C2:C64,Inventario!A2:A64,A8) -> 2 | C8: =SUMIFS(Inventario!$K$2:$K$64,Inventario!$A$2:$A$64,A8) -> 110000
A9: Set Negro | B9: =SUMIFS(Inventario!C2:C64,Inventario!A2:A64,A9) -> 3 | C9: =SUMIFS(Inventario!$K$2:$K$64,Inventario!$A$2:$A$64,A9) -> 225000
A10: Set corto Beige | B10: =SUMIFS(Inventario!C2:C64,Inventario!A2:A64,A10) -> 2 | C10: =SUMIFS(Inventario!$K$2:$K$64,Inventario!$A$2:$A$64,A10) -> 110000
A11: Set Blanco | B11: =SUMIFS(Inventario!C2:C64,Inventario!A2:A64,A11) -> 10 | C11: =SUMIFS(Inventario!$K$2:$K$64,Inventario!$A$2:$A$64,A11) -> 750000
A12: Urbano Fit | B12: =SUMIFS(Inventario!C2:C64,Inventario!A2:A64,A12) -> 1 | C12: =SUMIFS(Inventario!$K$2:$K$64,Inventario!$A$2:$A$64,A12) -> 50000
A13: Set corto Blanco + Beige | B13: =SUMIFS(Inventario!C2:C64,Inventario!A2:A64,A13) -> 11 | C13: =SUMIFS(Inventario!$K$2:$K$64,Inventario!$A$2:$A$64,A13) -> 622897
A14: Polo albaricoque | B14: =SUMIFS(Inventario!C2:C64,Inventario!A2:A64,A14) -> 1 | C14: =SUMIFS(Inventario!$K$2:$K$64,Inventario!$A$2:$A$64,A14) -> 39000
A15: Pantalón caqui | B15: =SUMIFS(Inventario!C2:C64,Inventario!A2:A64,A15) -> 0 | C15: =SUMIFS(Inventario!$K$2:$K$64,Inventario!$A$2:$A$64,A15) -> 0
A16: Camisetas negro | B16: =SUMIFS(Inventario!C2:C64,Inventario!A2:A64,A16) -> 9 | C16: =SUMIFS(Inventario!$K$2:$K$64,Inventario!$A$2:$A$64,A16) -> 315000
A17: Camisetas Azul oscuro | B17: =SUMIFS(Inventario!C2:C64,Inventario!A2:A64,A17) -> 5 | C17: =SUMIFS(Inventario!$K$2:$K$64,Inventario!$A$2:$A$64,A17) -> 175000
A18: Pantalón negro | B18: =SUMIFS(Inventario!C2:C64,Inventario!A2:A64,A18) -> 2 | C18: =SUMIFS(Inventario!$K$2:$K$64,Inventario!$A$2:$A$64,A18) -> 68000
A19: Camiseta Vinotinto | B19: =SUMIFS(Inventario!C2:C64,Inventario!A2:A64,A19) -> 4 | C19: =SUMIFS(Inventario!$K$2:$K$64,Inventario!$A$2:$A$64,A19) -> 140000
A20: TOTAL GENERAL | B20: =SUM(B2:B19) -> 80 | C20: =SUM(C2:C19) -> 3979097
